pyxmler/__init__.py
pyxmler/parser.py
pyxmler-0.3.0.dist-info/LICENSE
pyxmler-0.3.0.dist-info/WHEEL
pyxmler-0.3.0.dist-info/METADATA
pyxmler-0.3.0.dist-info/RECORD
