Metadata-Version: 2.1
Name: pyxmler
Version: 0.3.0
Summary: Converts a Python dictionary into a valid XML string
Home-page: https://github.com/rtician/pyxmler
License: GPL-2.0
Author: Ramiro Tician
Author-email: ramirotician@gmail.com
Requires-Python: >=3.4,<4.0
Classifier: Development Status :: 5 - Production/Stable
Classifier: Intended Audience :: Developers
Classifier: License :: OSI Approved :: GNU General Public License v2 (GPLv2)
Classifier: Operating System :: OS Independent
Classifier: Programming Language :: Python :: 3
Classifier: Programming Language :: Python :: 3.4
Classifier: Programming Language :: Python :: 3.5
Classifier: Programming Language :: Python :: 3.6
Classifier: Programming Language :: Python :: 3.7
Classifier: Programming Language :: Python :: 3.8
Classifier: Topic :: Software Development :: Libraries
Project-URL: Repository, https://github.com/rtician/pyxmler
